MANIFEST.in
README.md
setup.py
symbolator/__init__.py
symbolator/asp.py
symbolator/utils.py
symbolator/version.py
symbolator/client/__init__.py
symbolator/client/compare.py
symbolator/client/compat.py
symbolator/client/generate.py
symbolator/client/smeagle.py
symbolator/client/splice.py
symbolator/corpus/__init__.py
symbolator/corpus/base.py
symbolator/corpus/elf.py
symbolator/facts/__init__.py
symbolator/facts/compare_libs.lp
symbolator/facts/is_compatible.lp
symbolator/facts/missing_symbols.lp
symbolator/facts/stability.lp
symbolator/smeagle/__init__.py
symbolator/smeagle/model.py
symbolator/smeagle/schema.py
symbolator_python.egg-info/PKG-INFO
symbolator_python.egg-info/SOURCES.txt
symbolator_python.egg-info/dependency_links.txt
symbolator_python.egg-info/entry_points.txt
symbolator_python.egg-info/not-zip-safe
symbolator_python.egg-info/requires.txt
symbolator_python.egg-info/top_level.txt